pypylookup/__init__.py
pypylookup/pypylookup.py
pypylookup-0.0.1.dist-info/METADATA
pypylookup-0.0.1.dist-info/WHEEL
pypylookup-0.0.1.dist-info/top_level.txt
pypylookup-0.0.1.dist-info/RECORD
